[
    {
        "id": 1,
        "name": "张山",
        "nickname": "张三",
        "gender": "男",
        "jieduRoom": "1201",
        "time": "2019-12-12",
        "reason": "不详",
        "unit": "北京第三戒毒所",
        "deadTimeLimit": "3个月",
        "decideOffice": "北京第三戒毒所",
        "rusuoFile": "一号文件",
        "jieduStart": "2019-12-12",
        "jieduEnd": "2020-3-12"
    },
    {
        "id": 2,
        "name": "张山",
        "nickname": "张三",
        "gender": "男",
        "jieduRoom": "1201",
        "time": "2019-12-12",
        "reason": "不详",
        "unit": "北京第三戒毒所",
        "deadTimeLimit": "3个月",
        "decideOffice": "北京第三戒毒所",
        "rusuoFile": "一号文件",
        "jieduStart": "2019-12-12",
        "jieduEnd": "2020-3-12"
    },
    {
        "id": 3,
        "name": "张山",
        "nickname": "张三",
        "gender": "男",
        "jieduRoom": "1201",
        "time": "2019-12-12",
        "reason": "不详",
        "unit": "北京第三戒毒所",
        "deadTimeLimit": "3个月",
        "decideOffice": "北京第三戒毒所",
        "rusuoFile": "一号文件",
        "jieduStart": "2019-12-12",
        "jieduEnd": "2020-3-12"
    },
    {
        "id": 4,
        "name": "张山",
        "nickname": "张三",
        "gender": "男",
        "jieduRoom": "1201",
        "time": "2019-12-12",
        "reason": "不详",
        "unit": "北京第三戒毒所",
        "deadTimeLimit": "3个月",
        "decideOffice": "北京第三戒毒所",
        "rusuoFile": "一号文件",
        "jieduStart": "2019-12-12",
        "jieduEnd": "2020-3-12"
    },
    {
        "id": 5,
        "name": "张山",
        "nickname": "张三",
        "gender": "男",
        "jieduRoom": "1201",
        "time": "2019-12-12",
        "reason": "不详",
        "unit": "北京第三戒毒所",
        "deadTimeLimit": "3个月",
        "decideOffice": "北京第三戒毒所",
        "rusuoFile": "一号文件",
        "jieduStart": "2019-12-12",
        "jieduEnd": "2020-3-12"
    },
    {
        "id": 6,
        "name": "张山",
        "nickname": "张三",
        "gender": "男",
        "jieduRoom": "1201",
        "time": "2019-12-12",
        "reason": "不详",
        "unit": "北京第三戒毒所",
        "deadTimeLimit": "3个月",
        "decideOffice": "北京第三戒毒所",
        "rusuoFile": "一号文件",
        "jieduStart": "2019-12-12",
        "jieduEnd": "2020-3-12"
    },
    {
        "id": 7,
        "name": "张山",
        "nickname": "张三",
        "gender": "男",
        "jieduRoom": "1201",
        "time": "2019-12-12",
        "reason": "不详",
        "unit": "北京第三戒毒所",
        "deadTimeLimit": "3个月",
        "decideOffice": "北京第三戒毒所",
        "rusuoFile": "一号文件",
        "jieduStart": "2019-12-12",
        "jieduEnd": "2020-3-12"
    },
    {
        "id": 8,
        "name": "张山",
        "nickname": "张三",
        "gender": "男",
        "jieduRoom": "1201",
        "time": "2019-12-12",
        "reason": "不详",
        "unit": "北京第三戒毒所",
        "deadTimeLimit": "3个月",
        "decideOffice": "北京第三戒毒所",
        "rusuoFile": "一号文件",
        "jieduStart": "2019-12-12",
        "jieduEnd": "2020-3-12"
    },
    {
        "id": 9,
        "name": "张山",
        "nickname": "张三",
        "gender": "男",
        "jieduRoom": "1201",
        "time": "2019-12-12",
        "reason": "不详",
        "unit": "北京第三戒毒所",
        "deadTimeLimit": "3个月",
        "decideOffice": "北京第三戒毒所",
        "rusuoFile": "一号文件",
        "jieduStart": "2019-12-12",
        "jieduEnd": "2020-3-12"
    },
    {
        "id": 10,
        "name": "张山",
        "nickname": "张三",
        "gender": "男",
        "jieduRoom": "1201",
        "time": "2019-12-12",
        "reason": "不详",
        "unit": "北京第三戒毒所",
        "deadTimeLimit": "3个月",
        "decideOffice": "北京第三戒毒所",
        "rusuoFile": "一号文件",
        "jieduStart": "2019-12-12",
        "jieduEnd": "2020-3-12"
    }
]